joshpdf/__init__.py
joshpdf/pdf2text.py
josh22pdf-1.1.dist-info/LICENSE
josh22pdf-1.1.dist-info/METADATA
josh22pdf-1.1.dist-info/WHEEL
josh22pdf-1.1.dist-info/top_level.txt
josh22pdf-1.1.dist-info/RECORD
