Metadata-Version: 2.1
Name: josh22pdf
Version: 1.1
License-File: LICENSE
